arxiv_daily/__init__.py
arxiv_daily/agents.py
arxiv_daily/chains.py
arxiv_daily/cli.py
arxiv_daily/core.py
arxiv_daily/llm_client.py
arxiv_daily/py.typed
arxiv_daily/utils.py
arxiv_daily-0.1.3.dist-info/METADATA
arxiv_daily-0.1.3.dist-info/WHEEL
arxiv_daily-0.1.3.dist-info/entry_points.txt
arxiv_daily-0.1.3.dist-info/licenses/LICENSE
arxiv_daily-0.1.3.dist-info/RECORD
