Metadata-Version: 2.4
Name: arxiv-daily
Version: 0.1.3
Summary: Tracking daily arXiv updates and generating intelligent summaries with LLMs.
Project-URL: Repository, https://github.com/GZU-MuTian/arxiv-daily
Author-email: yuliu <yuliu@gzu.edu.cn>
License-File: LICENSE
Requires-Python: >=3.11
Requires-Dist: beautifulsoup4>=4.14.3
Requires-Dist: langchain-community>=0.4.1
Requires-Dist: langchain-deepseek>=1.0.1
Requires-Dist: langchain-ollama>=1.0.1
Requires-Dist: langchain>=1.2.0
Requires-Dist: langgraph>=1.0.5
Requires-Dist: python-dotenv>=1.2.1
Requires-Dist: rich>=14.2.0
Requires-Dist: typer>=0.21.0
